netcontrol/__init__.py
netcontrol/fabric/__init__.py
netcontrol/fabric/fabric.py
netcontrol/fabric/tests.py
netcontrol/fortigate/__init__.py
netcontrol/fortigate/fortigate.py
netcontrol/fortiswitch/__init__.py
netcontrol/fortiswitch/fortiswitch.py
netcontrol/fpoc/__init__.py
netcontrol/fpoc/fpoc.py
netcontrol/ssh/__init__.py
netcontrol/ssh/ssh.py
netcontrol/ssh/test2_paramiko.py
netcontrol/ssh/test3_paramiko.py
netcontrol/ssh/test4.py
netcontrol/ssh/test4_paramiko.py
netcontrol/ssh/test_paramiko.py
netcontrol/vm/__init__.py
netcontrol/vm/vm.py
netcontrol/vyos/__init__.py
netcontrol/vyos/vyos.py
netcontrol-1.107.dist-info/LICENSE
netcontrol-1.107.dist-info/METADATA
netcontrol-1.107.dist-info/WHEEL
netcontrol-1.107.dist-info/top_level.txt
netcontrol-1.107.dist-info/RECORD
